MasterDef/__init__.py
MasterDef/formatting.py
MasterDef/validation.py
masterdef-0.1.dist-info/METADATA
masterdef-0.1.dist-info/WHEEL
masterdef-0.1.dist-info/top_level.txt
masterdef-0.1.dist-info/RECORD
